{"nodes": [{"id": "src_api_client_model_enum_public_ts", "label": "public.ts", "file_type": "code", "source_file": "src/api-client/model-enum/public.ts", "source_location": "L1"}, {"id": "public_querymodelenumcontext", "label": "queryModelEnumContext()", "file_type": "code", "source_file": "src/api-client/model-enum/public.ts", "source_location": "L17"}, {"id": "public_createenumfield", "label": "createEnumField()", "file_type": "code", "source_file": "src/api-client/model-enum/public.ts", "source_location": "L62"}, {"id": "public_updatefieldmeta", "label": "updateFieldMeta()", "file_type": "code", "source_file": "src/api-client/model-enum/public.ts", "source_location": "L66"}], "edges": [{"source": "src_api_client_model_enum_public_ts", "target": "client", "relation": "imports_from", "confidence": "EXTRACTED", "source_file": "src/api-client/model-enum/public.ts", "source_location": "L1", "weight": 1.0}, {"source": "src_api_client_model_enum_public_ts", "target": "src_api_client_model_enum_mock_client", "relation": "imports_from", "confidence": "EXTRACTED", "source_file": "src/api-client/model-enum/public.ts", "source_location": "L2", "weight": 1.0}, {"source": "src_api_client_model_enum_public_ts", "target": "src_api_client_model_enum_graphql_docs", "relation": "imports_from", "confidence": "EXTRACTED", "source_file": "src/api-client/model-enum/public.ts", "source_location": "L6", "weight": 1.0}, {"source": "src_api_client_model_enum_public_ts", "target": "graphql", "relation": "imports_from", "confidence": "EXTRACTED", "source_file": "src/api-client/model-enum/public.ts", "source_location": "L7", "weight": 1.0}, {"source": "src_api_client_model_enum_public_ts", "target": "types", "relation": "imports_from", "confidence": "EXTRACTED", "source_file": "src/api-client/model-enum/public.ts", "source_location": "L8", "weight": 1.0}, {"source": "src_api_client_model_enum_public_ts", "target": "src_api_client_model_enum_types", "relation": "imports_from", "confidence": "EXTRACTED", "source_file": "src/api-client/model-enum/public.ts", "source_location": "L9", "weight": 1.0}, {"source": "src_api_client_model_enum_public_ts", "target": "public_querymodelenumcontext", "relation": "contains", "confidence": "EXTRACTED", "source_file": "src/api-client/model-enum/public.ts", "source_location": "L17", "weight": 1.0}, {"source": "src_api_client_model_enum_public_ts", "target": "public_createenumfield", "relation": "contains", "confidence": "EXTRACTED", "source_file": "src/api-client/model-enum/public.ts", "source_location": "L62", "weight": 1.0}, {"source": "src_api_client_model_enum_public_ts", "target": "public_updatefieldmeta", "relation": "contains", "confidence": "EXTRACTED", "source_file": "src/api-client/model-enum/public.ts", "source_location": "L66", "weight": 1.0}]}