{"nodes": [{"id": "modelcraft_front_src_app_org_orgname_project_projectslug_rbac_permissions_new_page_tsx", "label": "page.tsx", "file_type": "code", "source_file": "modelcraft-front/src/app/org/[orgName]/project/[projectSlug]/rbac/permissions/new/page.tsx", "source_location": "L1"}, {"id": "page_actioncard", "label": "ActionCard()", "file_type": "code", "source_file": "modelcraft-front/src/app/org/[orgName]/project/[projectSlug]/rbac/permissions/new/page.tsx", "source_location": "L71"}, {"id": "page_cn", "label": "cn()", "file_type": "code", "source_file": "modelcraft-front/src/app/org/[orgName]/project/[projectSlug]/rbac/permissions/new/page.tsx", "source_location": "L140"}, {"id": "page_handlenext", "label": "handleNext()", "file_type": "code", "source_file": "modelcraft-front/src/app/org/[orgName]/project/[projectSlug]/rbac/permissions/new/page.tsx", "source_location": "L344"}], "edges": [{"source": "modelcraft_front_src_app_org_orgname_project_projectslug_rbac_permissions_new_page_tsx", "target": "react", "relation": "imports_from", "confidence": "EXTRACTED", "source_file": "modelcraft-front/src/app/org/[orgName]/project/[projectSlug]/rbac/permissions/new/page.tsx", "source_location": "L3", "weight": 1.0}, {"source": "modelcraft_front_src_app_org_orgname_project_projectslug_rbac_permissions_new_page_tsx", "target": "navigation", "relation": "imports_from", "confidence": "EXTRACTED", "source_file": "modelcraft-front/src/app/org/[orgName]/project/[projectSlug]/rbac/permissions/new/page.tsx", "source_location": "L4", "weight": 1.0}, {"source": "modelcraft_front_src_app_org_orgname_project_projectslug_rbac_permissions_new_page_tsx", "target": "lucide_react", "relation": "imports_from", "confidence": "EXTRACTED", "source_file": "modelcraft-front/src/app/org/[orgName]/project/[projectSlug]/rbac/permissions/new/page.tsx", "source_location": "L5", "weight": 1.0}, {"source": "modelcraft_front_src_app_org_orgname_project_projectslug_rbac_permissions_new_page_tsx", "target": "sonner", "relation": "imports_from", "confidence": "EXTRACTED", "source_file": "modelcraft-front/src/app/org/[orgName]/project/[projectSlug]/rbac/permissions/new/page.tsx", "source_location": "L6", "weight": 1.0}, {"source": "modelcraft_front_src_app_org_orgname_project_projectslug_rbac_permissions_new_page_tsx", "target": "button", "relation": "imports_from", "confidence": "EXTRACTED", "source_file": "modelcraft-front/src/app/org/[orgName]/project/[projectSlug]/rbac/permissions/new/page.tsx", "source_location": "L8", "weight": 1.0}, {"source": "modelcraft_front_src_app_org_orgname_project_projectslug_rbac_permissions_new_page_tsx", "target": "input", "relation": "imports_from", "confidence": "EXTRACTED", "source_file": "modelcraft-front/src/app/org/[orgName]/project/[projectSlug]/rbac/permissions/new/page.tsx", "source_location": "L9", "weight": 1.0}, {"source": "modelcraft_front_src_app_org_orgname_project_projectslug_rbac_permissions_new_page_tsx", "target": "label", "relation": "imports_from", "confidence": "EXTRACTED", "source_file": "modelcraft-front/src/app/org/[orgName]/project/[projectSlug]/rbac/permissions/new/page.tsx", "source_location": "L10", "weight": 1.0}, {"source": "modelcraft_front_src_app_org_orgname_project_projectslug_rbac_permissions_new_page_tsx", "target": "textarea", "relation": "imports_from", "confidence": "EXTRACTED", "source_file": "modelcraft-front/src/app/org/[orgName]/project/[projectSlug]/rbac/permissions/new/page.tsx", "source_location": "L11", "weight": 1.0}, {"source": "modelcraft_front_src_app_org_orgname_project_projectslug_rbac_permissions_new_page_tsx", "target": "select", "relation": "imports_from", "confidence": "EXTRACTED", "source_file": "modelcraft-front/src/app/org/[orgName]/project/[projectSlug]/rbac/permissions/new/page.tsx", "source_location": "L12", "weight": 1.0}, {"source": "modelcraft_front_src_app_org_orgname_project_projectslug_rbac_permissions_new_page_tsx", "target": "rbac", "relation": "imports_from", "confidence": "EXTRACTED", "source_file": "modelcraft-front/src/app/org/[orgName]/project/[projectSlug]/rbac/permissions/new/page.tsx", "source_location": "L19", "weight": 1.0}, {"source": "modelcraft_front_src_app_org_orgname_project_projectslug_rbac_permissions_new_page_tsx", "target": "modelcraft_front_src_app_org_orgname_project_projectslug_rbac_permissions_new_hooks_usecreatepermissionwizard", "relation": "imports_from", "confidence": "EXTRACTED", "source_file": "modelcraft-front/src/app/org/[orgName]/project/[projectSlug]/rbac/permissions/new/page.tsx", "source_location": "L21", "weight": 1.0}, {"source": "modelcraft_front_src_app_org_orgname_project_projectslug_rbac_permissions_new_page_tsx", "target": "types", "relation": "imports_from", "confidence": "EXTRACTED", "source_file": "modelcraft-front/src/app/org/[orgName]/project/[projectSlug]/rbac/permissions/new/page.tsx", "source_location": "L25", "weight": 1.0}, {"source": "modelcraft_front_src_app_org_orgname_project_projectslug_rbac_permissions_new_page_tsx", "target": "utils", "relation": "imports_from", "confidence": "EXTRACTED", "source_file": "modelcraft-front/src/app/org/[orgName]/project/[projectSlug]/rbac/permissions/new/page.tsx", "source_location": "L26", "weight": 1.0}, {"source": "modelcraft_front_src_app_org_orgname_project_projectslug_rbac_permissions_new_page_tsx", "target": "page_actioncard", "relation": "contains", "confidence": "EXTRACTED", "source_file": "modelcraft-front/src/app/org/[orgName]/project/[projectSlug]/rbac/permissions/new/page.tsx", "source_location": "L71", "weight": 1.0}, {"source": "modelcraft_front_src_app_org_orgname_project_projectslug_rbac_permissions_new_page_tsx", "target": "page_cn", "relation": "contains", "confidence": "EXTRACTED", "source_file": "modelcraft-front/src/app/org/[orgName]/project/[projectSlug]/rbac/permissions/new/page.tsx", "source_location": "L140", "weight": 1.0}, {"source": "modelcraft_front_src_app_org_orgname_project_projectslug_rbac_permissions_new_page_tsx", "target": "page_handlenext", "relation": "contains", "confidence": "EXTRACTED", "source_file": "modelcraft-front/src/app/org/[orgName]/project/[projectSlug]/rbac/permissions/new/page.tsx", "source_location": "L344", "weight": 1.0}]}